{"stats":{"covid":[{"range":"0 - 9","cases":230436,"hosp":927,"death":3,"pop":876803},{"range":"10 - 19","cases":414645,"hosp":395,"death":1,"pop":849498},{"range":"20 - 29","cases":470406,"hosp":1080,"death":5,"pop":1038134},{"range":"30 - 39","cases":515660,"hosp":2054,"death":21,"pop":1243230},{"range":"40 - 49","cases":454564,"hosp":3399,"death":64,"pop":1201477},{"range":"50 - 59","cases":357701,"hosp":6250,"death":301,"pop":1299109},{"range":"60 - 69","cases":179907,"hosp":7922,"death":925,"pop":967293},{"range":"70 - 79","cases":91077,"hosp":10543,"death":2547,"pop":736467},{"range":"80+","cases":77989,"hosp":14029,"death":8819,"pop":458289},{"range":"Unbekannt","cases":628,"hosp":1,"death":0,"pop":0}],"vacc":[{"range":"0 - 9","vaccinated":19293,"pop":876803},{"range":"10 - 19","vaccinated":407560,"pop":849498},{"range":"20 - 29","vaccinated":740056,"pop":1038134},{"range":"30 - 39","vaccinated":908907,"pop":1243230},{"range":"40 - 49","vaccinated":927683,"pop":1201477},{"range":"50 - 59","vaccinated":1045381,"pop":1299109},{"range":"60 - 69","vaccinated":833028,"pop":967293},{"range":"70 - 79","vaccinated":669313,"pop":736467},{"range":"80+","vaccinated":432302,"pop":458289},{"range":"Unbekannt","vaccinated":0,"pop":0}]},"years":{"covid":[{"year":"2020","cases":460862,"hosp":20412,"death":7812},{"year":"2021","cases":912386,"hosp":19979,"death":4138},{"year":"2022","cases":1419765,"hosp":6209,"death":736}],"vacc":[{"year":"2020","vaccinated":26},{"year":"2021","vaccinated":11668815},{"year":"2022","vaccinated":298021}]},"date":{"start":"2020-02-24T00:00:00.000Z","end":"2022-03-05T00:00:00.000Z"}}