{"stats":{"covid":[{"range":"0 - 9","cases":276899,"hosp":1500,"death":6,"pop":883904},{"range":"10 - 19","cases":524602,"hosp":552,"death":3,"pop":858994},{"range":"20 - 29","cases":680081,"hosp":1354,"death":5,"pop":1027732},{"range":"30 - 39","cases":797507,"hosp":2488,"death":24,"pop":1254957},{"range":"40 - 49","cases":707010,"hosp":3891,"death":77,"pop":1205539},{"range":"50 - 59","cases":635912,"hosp":7263,"death":336,"pop":1300012},{"range":"60 - 69","cases":363488,"hosp":9864,"death":1006,"pop":991217},{"range":"70 - 79","cases":217452,"hosp":14628,"death":2782,"pop":744449},{"range":"80+","cases":160199,"hosp":21363,"death":9562,"pop":471987},{"range":"Unbekannt","cases":753,"hosp":1,"death":0,"pop":0}],"vacc":[{"range":"0 - 9","vaccinated":25386,"pop":883904},{"range":"10 - 19","vaccinated":417807,"pop":858994},{"range":"20 - 29","vaccinated":742842,"pop":1027732},{"range":"30 - 39","vaccinated":911850,"pop":1254957},{"range":"40 - 49","vaccinated":929401,"pop":1205539},{"range":"50 - 59","vaccinated":1046632,"pop":1300012},{"range":"60 - 69","vaccinated":834362,"pop":991217},{"range":"70 - 79","vaccinated":669764,"pop":744449},{"range":"80+","vaccinated":433382,"pop":471987},{"range":"Unbekannt","vaccinated":0,"pop":0}]},"years":{"covid":[{"year":"2020","cases":460837,"hosp":20491,"death":7823},{"year":"2021","cases":912339,"hosp":20051,"death":4152},{"year":"2022","cases":2990727,"hosp":22362,"death":1826}],"vacc":[{"year":"2020","vaccinated":26},{"year":"2021","vaccinated":11661212},{"year":"2022","vaccinated":361614}]},"date":{"start":"2020-02-24T00:00:00.000Z","end":"2022-12-24T00:00:00.000Z"}}